uipath/runtime/__init__.py
uipath/runtime/base.py
uipath/runtime/context.py
uipath/runtime/factory.py
uipath/runtime/py.typed
uipath/runtime/registry.py
uipath/runtime/result.py
uipath/runtime/schema.py
uipath/runtime/chat/__init__.py
uipath/runtime/chat/protocol.py
uipath/runtime/chat/runtime.py
uipath/runtime/debug/__init__.py
uipath/runtime/debug/breakpoint.py
uipath/runtime/debug/exception.py
uipath/runtime/debug/protocol.py
uipath/runtime/debug/runtime.py
uipath/runtime/errors/__init__.py
uipath/runtime/errors/codes.py
uipath/runtime/errors/contract.py
uipath/runtime/errors/exception.py
uipath/runtime/events/__init__.py
uipath/runtime/events/base.py
uipath/runtime/events/state.py
uipath/runtime/logging/__init__.py
uipath/runtime/logging/_context.py
uipath/runtime/logging/_filters.py
uipath/runtime/logging/_interceptor.py
uipath/runtime/logging/_writers.py
uipath/runtime/logging/handlers.py
uipath/runtime/resumable/__init__.py
uipath/runtime/resumable/protocols.py
uipath/runtime/resumable/runtime.py
uipath/runtime/resumable/trigger.py
uipath_runtime-0.5.0.dist-info/METADATA
uipath_runtime-0.5.0.dist-info/WHEEL
uipath_runtime-0.5.0.dist-info/licenses/LICENSE
uipath_runtime-0.5.0.dist-info/RECORD
