Metadata-Version: 2.4
Name: uipath-runtime
Version: 0.5.0
Summary: Runtime abstractions and interfaces for building agents and automation scripts in the UiPath ecosystem
Project-URL: Homepage, https://uipath.com
Project-URL: Repository, https://github.com/UiPath/uipath-runtime-python
Project-URL: Documentation, https://uipath.github.io/uipath-python/
Maintainer-email: Cristian Pufu <cristian.pufu@uipath.com>
License-File: LICENSE
Classifier: Intended Audience :: Developers
Classifier: Programming Language :: Python :: 3.11
Classifier: Programming Language :: Python :: 3.12
Classifier: Programming Language :: Python :: 3.13
Classifier: Topic :: Software Development :: Build Tools
Requires-Python: >=3.11
Requires-Dist: uipath-core<0.2.0,>=0.1.1
